LICENSE.md
MANIFEST.in
README.rst
pyproject.toml
requirements.core.txt
setup.py
core_dashboard_app/__init__.py
core_dashboard_app/admin.py
core_dashboard_app/menus.py
core_dashboard_app/settings.py
core_dashboard_app/urls.py
core_dashboard_app.egg-info/PKG-INFO
core_dashboard_app.egg-info/SOURCES.txt
core_dashboard_app.egg-info/dependency_links.txt
core_dashboard_app.egg-info/requires.txt
core_dashboard_app.egg-info/top_level.txt
core_dashboard_app/static/core_dashboard_app/admin/js/my_dashboard_tabs.raw.js
core_dashboard_app/static/core_dashboard_app/common/css/my_dashboard_tabs.css
core_dashboard_app/static/core_dashboard_app/common/js/my_dashboard_tabs.js
core_dashboard_app/static/core_dashboard_app/user/js/my_dashboard_tabs.raw.js
core_dashboard_app/templates/core_dashboard_app/admin/my_dashboard_container.html
core_dashboard_app/templates/core_dashboard_app/admin/my_dashboard_content.html
core_dashboard_app/templates/core_dashboard_app/common/list/my_dashboard_tabs.html
core_dashboard_app/templates/core_dashboard_app/common/list/my_dashboard_tabs_file_pagination.html
core_dashboard_app/templates/core_dashboard_app/common/pagination/pagination_tab.html
core_dashboard_app/templates/core_dashboard_app/user/my_dashboard_container.html
core_dashboard_app/views/__init__.py
core_dashboard_app/views/common/__init__.py
core_dashboard_app/views/common/views.py
docs/__init__.py
docs/conf.py
docs/conf_urls.py
tests/__init__.py
tests/test_settings.py
tests/urls.py
tests/views/__init__.py
tests/views/fixtures.py
tests/views/common/__init__.py
tests/views/common/views/__init__.py
tests/views/common/views/tests_int.py
tests/views/common/views/tests_unit.py