Metadata-Version: 2.1
Name: core-dashboard-app
Version: 2.19.0
Summary: Resource management via a dashboard for the curator core project
Home-page: https://github.com/usnistgov/core_dashboard_app
Author: NIST IT Lab
Author-email: itl_inquiries@nist.gov
License-File: LICENSE.md
